ramses/__init__.py
ramses/main.py
ramses/status_codes.py
ramses/errors/__init__.py
ramses/errors/abstract.py
ramses/errors/http_4xx/__init__.py
ramses/errors/http_4xx/bad_request_error.py
ramses/errors/http_4xx/forbidden.py
ramses/errors/http_4xx/http_4xx_errors_mapper.py
ramses/errors/http_4xx/not_found_error.py
ramses/errors/http_4xx/unauthorized.py
ramses/errors/http_5xx/__init__.py
ramses/errors/http_5xx/http_5xx_errors_mapper.py
ramses/errors/http_5xx/internal_server_error.py
ramses/libs/__init__.py
ramses/libs/utils.py
ramses/responses/__init__.py
ramses/responses/json_response.py
ramses_wolasoft-0.0.2.dist-info/LICENSE
ramses_wolasoft-0.0.2.dist-info/METADATA
ramses_wolasoft-0.0.2.dist-info/WHEEL
ramses_wolasoft-0.0.2.dist-info/top_level.txt
ramses_wolasoft-0.0.2.dist-info/RECORD
