Metadata-Version: 2.1
Name: ramses-wolasoft
Version: 0.0.2
Summary: A small flask based restful ramses
Home-page: https://github.com/wolasoft/ramses
Author: Komi Wolanyo KOUDO
Author-email: wolasoft@wolasoft.com
License: UNKNOWN
Keywords: flask,server,rest
Platform: UNKNOWN
Classifier: Programming Language :: Python :: 3
Classifier: License :: OSI Approved :: MIT License
Classifier: Operating System :: OS Independent
Requires-Python: >=3
Requires-Dist: Flask (==1.0.3)
Requires-Dist: Flask-Cors (==3.0.7)
Requires-Dist: Flask-Log-Request-ID (==0.10.0)
Requires-Dist: stringcase (==1.2.0)
